{"query": {"seed_index": 0, "x": 0, "y": 0, "w": 15, "h": 15, "phase": "phase1", "tile_id": "s0_p1t0"}, "response": {"grid": [[10, 10, 10, 10, 10, 10, 10, 10, 10, 10, 10, 10, 10, 10, 10], [10, 11, 4, 11, 1, 2, 1, 2, 4, 11, 11, 11, 4, 11, 11], [10, 11, 11, 11, 1, 4, 1, 11, 11, 11, 11, 11, 4, 11, 4], [10, 11, 4, 11, 11, 1, 4, 11, 11, 4, 4, 11, 11, 11, 4], [10, 11, 4, 11, 4, 11, 1, 4, 4, 11, 11, 11, 11, 11, 11], [10, 4, 11, 4, 11, 4, 11, 11, 11, 11, 4, 11, 11, 4, 4], [10, 11, 11, 4, 11, 11, 11, 11, 11, 11, 11, 11, 11, 4, 11], [10, 11, 11, 11, 4, 11, 4, 11, 11, 11, 11, 11, 11, 4, 3], [10, 11, 4, 11, 11, 4, 11, 5, 5, 5, 5, 5, 11, 5, 5], [10, 4, 11, 11, 11, 4, 11, 11, 5, 4, 4, 11, 11, 4, 5], [10, 11, 4, 11, 11, 11, 11, 11, 5, 11, 11, 11, 11, 1, 11], [10, 11, 11, 11, 4, 1, 11, 11, 11, 11, 4, 11, 11, 1, 11], [10, 11, 11, 11, 4, 1, 1, 11, 11, 11, 11, 11, 2, 11, 1], [10, 11, 11, 4, 1, 1, 1, 4, 11, 4, 4, 11, 10, 10, 2], [10, 11, 11, 11, 1, 2, 1, 4, 11, 4, 4, 10, 10, 11, 4]], "settlements": [{"x": 14, "y": 12, "has_port": false, "alive": true, "population": 2.416, "food": 0.311, "wealth": 0.02, "defense": 1.0, "owner_id": 10}, {"x": 12, "y": 12, "has_port": true, "alive": true, "population": 0.046, "food": 0.996, "wealth": 0.001, "defense": 0.022, "owner_id": 10}, {"x": 6, "y": 13, "has_port": false, "alive": true, "population": 2.027, "food": 0.642, "wealth": 0.017, "defense": 1.0, "owner_id": 39}, {"x": 13, "y": 11, "has_port": false, "alive": true, "population": 1.743, "food": 0.772, "wealth": 0.02, "defense": 1.0, "owner_id": 10}, {"x": 5, "y": 12, "has_port": false, "alive": true, "population": 1.735, "food": 0.648, "wealth": 0.017, "defense": 1.0, "owner_id": 39}, {"x": 5, "y": 1, "has_port": true, "alive": true, "population": 1.886, "food": 0.795, "wealth": 0.012, "defense": 1.0, "owner_id": 40}, {"x": 5, "y": 14, "has_port": true, "alive": true, "population": 1.59, "food": 0.481, "wealth": 0.002, "defense": 1.0, "owner_id": 39}, {"x": 4, "y": 2, "has_port": false, "alive": true, "population": 1.521, "food": 0.617, "wealth": 0.01, "defense": 1.0, "owner_id": 40}, {"x": 7, "y": 1, "has_port": true, "alive": true, "population": 1.489, "food": 0.874, "wealth": 0.014, "defense": 0.913, "owner_id": 40}, {"x": 5, "y": 3, "has_port": false, "alive": true, "population": 1.256, "food": 0.894, "wealth": 0.01, "defense": 0.752, "owner_id": 40}, {"x": 6, "y": 4, "has_port": false, "alive": true, "population": 0.963, "food": 0.919, "wealth": 0.009, "defense": 0.566, "owner_id": 40}, {"x": 4, "y": 13, "has_port": false, "alive": true, "population": 0.739, "food": 0.938, "wealth": 0.0, "defense": 0.435, "owner_id": 39}, {"x": 14, "y": 13, "has_port": true, "alive": true, "population": 0.464, "food": 0.961, "wealth": 0.002, "defense": 0.248, "owner_id": 10}, {"x": 4, "y": 14, "has_port": false, "alive": true, "population": 0.638, "food": 0.946, "wealth": 0.003, "defense": 0.357, "owner_id": 39}, {"x": 5, "y": 13, "has_port": false, "alive": true, "population": 0.5, "food": 0.292, "wealth": 0.004, "defense": 0.257, "owner_id": 39}, {"x": 5, "y": 11, "has_port": false, "alive": true, "population": 0.569, "food": 0.847, "wealth": 0.004, "defense": 0.262, "owner_id": 39}, {"x": 6, "y": 12, "has_port": false, "alive": true, "population": 0.426, "food": 0.544, "wealth": 0.0, "defense": 0.197, "owner_id": 39}, {"x": 13, "y": 10, "has_port": false, "alive": true, "population": 0.424, "food": 0.598, "wealth": 0.002, "defense": 0.161, "owner_id": 10}, {"x": 6, "y": 1, "has_port": false, "alive": true, "population": 0.5, "food": 0.297, "wealth": 0.003, "defense": 0.228, "owner_id": 40}, {"x": 6, "y": 14, "has_port": false, "alive": true, "population": 0.5, "food": 0.387, "wealth": 0.0, "defense": 0.228, "owner_id": 39}, {"x": 4, "y": 1, "has_port": false, "alive": true, "population": 0.5, "food": 0.212, "wealth": 0.002, "defense": 0.2, "owner_id": 40}], "viewport": {"x": 0, "y": 0, "w": 15, "h": 15}, "queries_used": 1, "queries_max": 50}}