{"query": {"seed_index": 0, "x": 24, "y": 24, "w": 15, "h": 15, "phase": "phase1", "tile_id": "s0_p1t3"}, "response": {"grid": [[1, 4, 10, 10, 11, 11, 4, 4, 11, 10, 10, 11, 11, 11, 11], [4, 10, 10, 11, 11, 11, 4, 11, 11, 10, 10, 10, 4, 11, 11], [11, 10, 10, 11, 11, 11, 11, 11, 11, 10, 11, 10, 11, 11, 11], [10, 2, 11, 4, 11, 4, 11, 11, 11, 11, 11, 11, 10, 10, 4], [5, 4, 11, 11, 11, 11, 1, 11, 11, 4, 11, 11, 4, 10, 10], [1, 11, 11, 4, 11, 4, 4, 11, 11, 11, 1, 1, 11, 11, 10], [4, 11, 4, 11, 4, 11, 11, 11, 11, 1, 11, 11, 11, 11, 10], [11, 11, 11, 11, 1, 11, 11, 11, 11, 11, 11, 4, 1, 1, 11], [10, 10, 10, 10, 10, 10, 10, 10, 10, 4, 1, 11, 1, 11, 4], [4, 2, 11, 1, 11, 4, 2, 2, 11, 1, 1, 11, 1, 1, 11], [11, 11, 11, 1, 4, 11, 11, 4, 11, 11, 11, 1, 1, 11, 11], [1, 11, 11, 11, 11, 11, 11, 11, 11, 1, 11, 11, 1, 4, 11], [11, 1, 1, 1, 11, 11, 11, 1, 1, 1, 11, 11, 1, 11, 11], [1, 11, 1, 1, 11, 3, 11, 11, 11, 1, 11, 1, 1, 1, 2], [4, 11, 4, 4, 4, 4, 4, 11, 11, 1, 2, 2, 4, 4, 11]], "settlements": [{"x": 26, "y": 37, "has_port": false, "alive": true, "population": 3.686, "food": 0.286, "wealth": 0.024, "defense": 1.0, "owner_id": 23}, {"x": 27, "y": 36, "has_port": false, "alive": true, "population": 3.178, "food": 0.168, "wealth": 0.01, "defense": 1.0, "owner_id": 23}, {"x": 25, "y": 33, "has_port": true, "alive": true, "population": 2.773, "food": 0.813, "wealth": 0.018, "defense": 1.0, "owner_id": 23}, {"x": 35, "y": 38, "has_port": true, "alive": true, "population": 2.793, "food": 0.296, "wealth": 0.009, "defense": 1.0, "owner_id": 19}, {"x": 31, "y": 33, "has_port": true, "alive": true, "population": 1.588, "food": 0.893, "wealth": 0.002, "defense": 0.883, "owner_id": 19}, {"x": 25, "y": 27, "has_port": true, "alive": true, "population": 1.941, "food": 0.869, "wealth": 0.012, "defense": 1.0, "owner_id": 23}, {"x": 33, "y": 36, "has_port": false, "alive": true, "population": 2.086, "food": 0.732, "wealth": 0.006, "defense": 1.0, "owner_id": 19}, {"x": 34, "y": 33, "has_port": false, "alive": true, "population": 2.571, "food": 0.411, "wealth": 0.012, "defense": 1.0, "owner_id": 19}, {"x": 24, "y": 24, "has_port": false, "alive": true, "population": 1.834, "food": 0.676, "wealth": 0.001, "defense": 0.7, "owner_id": 23}, {"x": 27, "y": 37, "has_port": false, "alive": true, "population": 1.772, "food": 0.881, "wealth": 0.006, "defense": 1.0, "owner_id": 23}, {"x": 38, "y": 37, "has_port": true, "alive": true, "population": 1.622, "food": 0.805, "wealth": 0.006, "defense": 1.0, "owner_id": 19}, {"x": 27, "y": 34, "has_port": false, "alive": true, "population": 1.565, "food": 0.894, "wealth": 0.002, "defense": 0.905, "owner_id": 23}, {"x": 34, "y": 38, "has_port": true, "alive": true, "population": 1.7, "food": 0.874, "wealth": 0.004, "defense": 1.0, "owner_id": 19}, {"x": 37, "y": 31, "has_port": false, "alive": true, "population": 1.785, "food": 0.88, "wealth": 0.002, "defense": 1.0, "owner_id": 19}, {"x": 36, "y": 32, "has_port": false, "alive": true, "population": 1.436, "food": 0.727, "wealth": 0.001, "defense": 0.948, "owner_id": 19}, {"x": 30, "y": 28, "has_port": false, "alive": true, "population": 1.661, "food": 0.888, "wealth": 0.003, "defense": 0.912, "owner_id": 4}, {"x": 37, "y": 33, "has_port": false, "alive": true, "population": 1.438, "food": 0.903, "wealth": 0.006, "defense": 0.781, "owner_id": 19}, {"x": 34, "y": 32, "has_port": false, "alive": true, "population": 1.522, "food": 0.897, "wealth": 0.006, "defense": 0.806, "owner_id": 19}, {"x": 36, "y": 36, "has_port": false, "alive": true, "population": 1.369, "food": 0.908, "wealth": 0.002, "defense": 0.742, "owner_id": 19}, {"x": 36, "y": 37, "has_port": false, "alive": true, "population": 0.617, "food": 0.958, "wealth": 0.001, "defense": 0.276, "owner_id": 19}, {"x": 37, "y": 37, "has_port": false, "alive": true, "population": 0.617, "food": 0.958, "wealth": 0.001, "defense": 0.276, "owner_id": 19}, {"x": 36, "y": 34, "has_port": false, "alive": true, "population": 0.613, "food": 0.646, "wealth": 0.0, "defense": 0.275, "owner_id": 19}, {"x": 33, "y": 37, "has_port": false, "alive": true, "population": 0.571, "food": 0.962, "wealth": 0.001, "defense": 0.265, "owner_id": 19}, {"x": 24, "y": 35, "has_port": false, "alive": true, "population": 0.624, "food": 0.958, "wealth": 0.0, "defense": 0.277, "owner_id": 23}, {"x": 36, "y": 33, "has_port": false, "alive": true, "population": 0.516, "food": 0.493, "wealth": 0.0, "defense": 0.256, "owner_id": 19}, {"x": 33, "y": 38, "has_port": false, "alive": true, "population": 0.571, "food": 0.718, "wealth": 0.001, "defense": 0.265, "owner_id": 19}, {"x": 25, "y": 36, "has_port": false, "alive": true, "population": 0.624, "food": 0.958, "wealth": 0.0, "defense": 0.277, "owner_id": 23}, {"x": 34, "y": 29, "has_port": false, "alive": true, "population": 0.617, "food": 0.958, "wealth": 0.001, "defense": 0.276, "owner_id": 19}, {"x": 31, "y": 36, "has_port": false, "alive": true, "population": 0.64, "food": 0.96, "wealth": 0.0, "defense": 0.245, "owner_id": 19}, {"x": 32, "y": 36, "has_port": false, "alive": true, "population": 0.505, "food": 0.796, "wealth": 0.001, "defense": 0.231, "owner_id": 19}, {"x": 33, "y": 33, "has_port": false, "alive": true, "population": 0.545, "food": 0.963, "wealth": 0.0, "defense": 0.238, "owner_id": 19}, {"x": 35, "y": 34, "has_port": false, "alive": true, "population": 0.55, "food": 0.963, "wealth": 0.001, "defense": 0.239, "owner_id": 19}, {"x": 24, "y": 37, "has_port": false, "alive": true, "population": 0.501, "food": 0.766, "wealth": 0.001, "defense": 0.19, "owner_id": 18}, {"x": 28, "y": 31, "has_port": false, "alive": true, "population": 0.634, "food": 0.93, "wealth": 0.004, "defense": 0.272, "owner_id": 23}, {"x": 36, "y": 35, "has_port": false, "alive": true, "population": 0.626, "food": 0.664, "wealth": 0.001, "defense": 0.271, "owner_id": 19}, {"x": 35, "y": 29, "has_port": false, "alive": true, "population": 0.626, "food": 0.659, "wealth": 0.003, "defense": 0.271, "owner_id": 19}, {"x": 27, "y": 33, "has_port": false, "alive": true, "population": 0.579, "food": 0.525, "wealth": 0.001, "defense": 0.222, "owner_id": 23}, {"x": 33, "y": 30, "has_port": false, "alive": true, "population": 0.626, "food": 0.907, "wealth": 0.0, "defense": 0.271, "owner_id": 19}, {"x": 33, "y": 35, "has_port": false, "alive": true, "population": 0.558, "food": 0.353, "wealth": 0.002, "defense": 0.233, "owner_id": 19}, {"x": 24, "y": 29, "has_port": false, "alive": true, "population": 0.477, "food": 0.475, "wealth": 0.002, "defense": 0.189, "owner_id": 23}, {"x": 35, "y": 37, "has_port": false, "alive": true, "population": 0.558, "food": 0.393, "wealth": 0.001, "defense": 0.233, "owner_id": 19}, {"x": 26, "y": 36, "has_port": false, "alive": true, "population": 0.5, "food": 0.172, "wealth": 0.005, "defense": 0.2, "owner_id": 23}, {"x": 36, "y": 31, "has_port": false, "alive": true, "population": 0.5, "food": 0.143, "wealth": 0.0, "defense": 0.2, "owner_id": 19}, {"x": 30, "y": 33, "has_port": true, "alive": true, "population": 0.4, "food": 0.179, "wealth": 0.0, "defense": 0.15, "owner_id": 19}], "viewport": {"x": 24, "y": 24, "w": 15, "h": 15}, "queries_used": 16, "queries_max": 50}}